sm_aicli/__init__.py
sm_aicli/main.py
sm_aicli/revision.py
sm_aicli/types.py
sm_aicli/utils.py
sm_aicli/actor/__init__.py
sm_aicli/actor/copilot.py
sm_aicli/actor/dummy.py
sm_aicli/actor/gpt4all.py
sm_aicli/actor/openai.py
sm_aicli/actor/user.py
sm_aicli-2.5.3.data/scripts/aicli
sm_aicli-2.5.3.dist-info/METADATA
sm_aicli-2.5.3.dist-info/WHEEL
sm_aicli-2.5.3.dist-info/top_level.txt
sm_aicli-2.5.3.dist-info/RECORD
