Metadata-Version: 2.1
Name: sm-aicli
Version: 2.5.3
Summary: Command-line interface for a number of AI models
Home-page: https://github.com/sergei-mironov/aicli
Author: Sergei Mironov
Author-email: sergei.v.mironov@proton.me
Classifier: Programming Language :: Python :: 3
Classifier: License :: OSI Approved :: Apache Software License
Classifier: Operating System :: POSIX :: Linux
Classifier: Topic :: Software Development :: Build Tools
Classifier: Intended Audience :: Developers
Classifier: Development Status :: 3 - Alpha
Requires-Python: >=3.6
Requires-Dist: gpt4all >=2.7.0
Requires-Dist: openai
Requires-Dist: gnureadline
Requires-Dist: lark
Requires-Dist: pillow
